Workbook

Sheet 현대로템
A1: 현대로템
A2: 45777
G4: (단위: 백만) | I4: *NOTE
B5: 주가 | C5: 유통주식수 | D5: 시가총액 | E5: ibd | F5: ltm ebit | G5: tax rate | I5: 분기보고서 내 주식의 총수 기재하지 않아 직전 사업보고서 사용
B6: 105000 | C6: =D24 -> 109142 | D6: =(B6*C6)/10^6 -> 11459.91 | E6: =SUMIF(A:A,E5,C:C)/10^3 -> 252879.68 | F6: =(H41+N41-J41)/1000 -> 614734.59 | G6: 0.264
B9: 4. 주식의 총수 등
B11: 가. 주식의 총수 현황
B12: (기준일 : | C12: 2024.12.31 | D12: ) | E12: (단위 : 천주, %)
B13: 구 분 | D13: 주식의 종류 | G13: 비고
D14: 보통주 | E14: 우선주 | F14: 합계
B15: Ⅰ. 발행할 주식의 총수 | D15: 200000 | E15: - | F15: 200000 | G15: 정관상 발행 가능한 주식 총수 : 2억주 (보통주/우선주 구분없음)
B16: Ⅱ. 현재까지 발행한 주식의 총수 | D16: 115742 | E16: - | F16: 115742 | G16: -
B17: Ⅲ. 현재까지 감소한 주식의 총수 | D17: 6600 | E17: - | F17: 6600 | G17: -
C18: 1. 감자 | D18: 6600 | E18: - | F18: 6600 | G18: -
C19: 2. 이익소각 | D19: - | E19: - | F19: - | G19: -
C20: 3. 상환주식의 상환 | D20: - | E20: - | F20: - | G20: -
C21: 4. 기타 | D21: - | E21: - | F21: - | G21: -
B22: Ⅳ. 발행주식의 총수 (Ⅱ-Ⅲ) | D22: 109142 | E22: - | F22: 109142 | G22: -
B23: Ⅴ. 자기주식수 | D23: - | E23: - | F23: - | G23: -
B24: Ⅵ. 유통주식수 (Ⅳ-Ⅴ) | D24: 109142 | E24: - | F24: 109142 | G24: -
B25: Ⅶ. 자기주식 보유비율 | D25: - | E25: - | F25: - | G25: -
B30: 2-1. 연결 재무상태표 | G30: 2-2. 연결 포괄손익계산서 | M30: 2-2. 연결 포괄손익계산서
B31: 연결 재무상태표 | G31: 연결 포괄손익계산서 | M31: 연결 포괄손익계산서
B32: 제 27 기 1분기말 2025.03.31 현재 | G32: 제 27 기 1분기 2025.01.01 부터 2025.03.31 까지 | M32: 제 26 기 2024.01.01 부터 2024.12.31 까지
B33: 제 26 기말 2024.12.31 현재 | G33: 제 26 기 1분기 2024.01.01 부터 2024.03.31 까지 | M33: 제 25 기 2023.01.01 부터 2023.12.31 까지
B34: (단위 : 천원) | G34: (단위 : 천원) | M34: 제 24 기 2022.01.01 부터 2022.12.31 까지
C35: 제 27 기 1분기말 | D35: 제 26 기말 | H35: 제 27 기 1분기 | J35: 제 26 기 1분기 | M35: (단위 : 천원)
B36: 자산 | H36: 3개월 | I36: 누적 | J36: 3개월 | K36: 누적 | N36: 제 26 기 | O36: 제 25 기 | P36: 제 24 기
B37: 유동자산 | C37: 3679870454 | D37: 3686316730 | G37: 매출액 (주26,27,36,38) | H37: 1176141098 | I37: 1176141098 | J37: 747779451 | K37: 747779451 | M37: 매출액 (주26,27,36,38) | N37: 4376597857 | O37: 3587382453 | P37: 3163343615
B38: 현금및현금성자산 (주4,21,35) | C38: 491247668 | D38: 472258339 | G38: 매출원가 (주31,36) | H38: 889997959 | I38: 889997959 | J38: 643123856 | K38: 643123856 | M38: 매출원가 (주31,36) | N38: 3547550219 | O38: 3122984003 | P38: 2797911962
B39: 유동매출채권 (주5,21,27,35,36) | C39: 724917369 | D39: 909369742 | G39: 매출총이익 | H39: 286143139 | I39: 286143139 | J39: 104655595 | K39: 104655595 | M39: 매출총이익 | N39: 829047638 | O39: 464398450 | P39: 365431653
B40: 기타유동채권 (주6,21,36) | C40: 61559596 | D40: 55767350 | G40: 판매비와관리비 (주28,31,36) | H40: 83290471 | I40: 83290471 | J40: 59971982 | K40: 59971982 | M40: 판매비와관리비 (주28,31,36) | N40: 372482104 | O40: 254351856 | P40: 217944984
B41: 계약자산 (주5,27,36) | C41: 805573731 | D41: 802137829 | G41: 영업손익 (주38) | H41: 202852668 | I41: 202852668 | J41: 44683613 | K41: 44683613 | M41: 영업손익 (주38) | N41: 456565534 | O41: 210046594 | P41: 147486669
B42: 기타금융자산 (주4,7,21,35,36) | C42: 294935032 | D42: 298218173 | G42: 기타수익 (주21,29) | H42: 9355776 | I42: 9355776 | J42: 16489906 | K42: 16489906 | M42: 기타수익 (주21,29) | N42: 114050169 | O42: 82308356 | P42: 99193218
B43: 재고자산 (주8) | C43: 414002821 | D43: 315635860 | G43: 기타비용 (주21,29,31) | H43: 21700992 | I43: 21700992 | J43: 13866557 | K43: 13866557 | M43: 기타비용 (주21,29,31) | N43: 84254421 | O43: 111691312 | P43: 94560825
B44: 당기법인세자산 | C44: 1243180 | D44: 1104397 | G44: 금융수익 (주21,30,36) | H44: 23305785 | I44: 23305785 | J44: 25614528 | K44: 25614528 | M44: 금융수익 (주21,30,36) | N44: 75210934 | O44: 47601139 | P44: 28547869
B45: 기타유동자산 (주9,21,36) | C45: 886391057 | D45: 831825040 | G45: 금융비용 (주21,30) | H45: 11159778 | I45: 11159778 | J45: 18576411 | K45: 18576411 | M45: 금융비용 (주21,30) | N45: 51904505 | O45: 47230751 | P45: 76639752
B46: 비유동자산 | C46: 1564572067 | D46: 1599078010 | G46: 지분법이익(손실) (주15) | H46: -21018 | I46: -21018 | J46: -12317 | K46: -12317 | M46: 지분법이익(손실) (주15) | N46: -106623 | O46: -193203 | P46: -146542
B47: 비유동매출채권 (주5,21,27,35,36) | C47: 25591121 | D47: 59228280 | G47: 법인세비용차감전순이익(손실) | H47: 202632441 | I47: 202632441 | J47: 54332762 | K47: 54332762 | M47: 법인세비용차감전순이익(손실) | N47: 509561088 | O47: 180840823 | P47: 103880637
B48: 장기기타채권 (주4,6,21,35,36) | C48: 16571515 | D48: 16643090 | G48: 법인세비용(수익) (주32) | H48: 45486441 | I48: 45486441 | J48: -1299913 | K48: -1299913 | M48: 법인세비용(수익) (주32) | N48: 104301674 | O48: 24061845 | P48: -90653616
... B55: 비유동 순확정급여자산 (주18) | C55: 0 | D55: 14499464 | G55: 분기총포괄손익 | H55: 160072292 | I55: 160072292 | J55: 56068931 | K55: 56068931 | M55: 당기손익으로 재분류될 수 있는 항목(세후기타포괄손익) | N55: -7416013 | O55: 10012772 | P55: 6096868
B56: 기타비유동자산 (주9) | C56: 15097660 | D56: 18579851 | G56: 분기순손익의 귀속 | M56: 세후파생상품평가이익(기타포괄손익) | N56: 0 | O56: 0 | P56: 1262933
B57: 이연법인세자산 | C57: 1065727 | D57: 2724331 | G57: 지배주주지분 분기순이익 | H57: 158385453 | I57: 158385453 | J57: 56241564 | K57: 56241564 | M57: 해외사업장환산외환차이(세후기타포괄손익) | N57: -7416013 | O57: 10012772 | P57: 4833935
B58: 자산총계 | C58: 5244442521 | D58: 5285394740 | G58: 비지배주주지분 | H58: -1239453 | I58: -1239453 | J58: -608889 | K58: -608889 | M58: 당기총포괄손익 | N58: 373023263 | O58: 155505565 | P58: 223225491
B59: 부채 | G59: 분기총포괄이익의 귀속 | M59: 당기순손익의 귀속
B60: 유동부채 | C60: 2846461845 | D60: 3019853718 | G60: 지배기업소유주지분 | H60: 162122523 | I60: 162122523 | J60: 56955771 | K60: 56955771 | M60: 지배기업의 소유주에게 귀속되는 당기순이익(손실) | N60: 406891810 | O60: 161027790 | P60: 197797542
B61: 매입채무 (주21,35,36) | C61: 414738381 | D61: 431986856 | G61: 비지배주주지분 | H61: -2050230 | I61: -2050230 | J61: -886840 | K61: -886840 | M61: 비지배주주지분 | N61: -1632396 | O61: -4248812 | P61: -3263289
B62: 미지급금 (주21,35,36) | C62: 77908995 | D62: 93076845 | G62: 주당손익 (주33) | M62: 당기총포괄이익의 귀속
B63: 계약부채 (주27,36) | C63: 1697227891 | D63: 1794227928 | G63: 기본주당이익(손실) (단위 : 원) | H63: 1451 | I63: 1451 | J63: 515 | K63: 515 | M63: 지배기업소유주지분 | N63: 376037452 | O63: 159507589 | P63: 227294805
A64: ibd | B64: 단기차입금 (주10,16,21,34,35,37) | C64: 63011799 | D64: 60392677 | M64: 비지배주주지분 (주39) | N64: -3014189 | O64: -4002024 | P64: -4069314
A65: ibd | B65: 유동성장기부채 (주10,16,21,34,35,37) | C65: 168628119 | D65: 261946020 | M65: 주당손익 (주33)
B66: 리스부채 (주17,34,35,36) | C66: 5382426 | D66: 6291998 | M66: 기본주당이익(손실) (단위 : 원) | N66: 3728 | O66: 1475 | P66: 1812
B67: 당기법인세부채 | C67: 55834990 | D67: 35180076
B68: 충당부채 (주19,27) | C68: 78732429 | D68: 80637987
B69: 기타유동부채 (주20,21,35,37) | C69: 284996815 | D69: 256113331
B70: 비유동부채 | C70: 250651654 | D70: 256455833
A71: ibd | B71: 장기차입금 (주10,16,21,34,35,37) | C71: 2600000 | D71: 2600000
A72: ibd | B72: 리스부채 (주17,34,35,36) | C72: 18639763 | D72: 19848947
B73: 비유동 순확정급여부채 (주18) | C73: 8342338 | D73: 220550
B74: 충당부채 (주19,37) | C74: 153275506 | D74: 155683451
B75: 기타비유동부채 (주20,21,35) | C75: 20466199 | D75: 20088926
B76: 이연법인세부채 | C76: 47327848 | D76: 58013959
B77: 부채총계 | C77: 3097113499 | D77: 3276309551
B78: 자본
B79: 지배기업소유주지분 | C79: 2185271886 | D79: 2044977823
B80: 자본금 (주1,22) | C80: 545711465 | D80: 545711465
B81: 기타불입자본 (주23) | C81: 519839907 | D81: 519839907
B82: 기타자본구성요소 (주24) | C82: 294278068 | D82: 290812699
B83: 이익잉여금(결손금) (주25) | C83: 825442446 | D83: 688613752
B84: 비지배지분 | C84: -37942864 | D84: -35892634
B85: 자본총계 | C85: 2147329022 | D85: 2009085189
B86: 부채와자본총계 | C86: 5244442521 | D86: 5285394740

Sheet wacc
B4: 기업명 | C4: Debt to Capital | D4: Equity to Capital | E4: Market Value of Total Equity | F4: IBD | G4: Capital | H4: LTM EBIT | I4: Tax Rate | J4: Leveraged Equity Beta | K4: Unleveraged Equity Beta | M4: D/E
B5: ='한국한공우주'!A1 -> 한국항공우주 | C5: =F5/G5 -> 0.14488969 | D5: =E5/G5 -> 0.85511031 | E5: ='한국한공우주'!D6 -> 7310633 | F5: ='한국한공우주'!E6 -> 1238712 | G5: =E5+F5 -> 8549345 | H5: ='한국한공우주'!F6 -> 239519.23 | I5: ='한국한공우주'!G6 -> 0.231 | M5: =C5/D5 -> 0.16943977
B6: ='두산에너빌리티'!A1 -> 두산에너빌리티 | C6: =F6/G6 -> 0.2579385 | D6: =E6/G6 -> 0.7420615 | E6: ='두산에너빌리티'!D6 -> 18541467 | F6: ='두산에너빌리티'!E6 -> 6444962 | G6: =E6+F6 -> 24986429 | H6: ='두산에너빌리티'!F6 -> 802004 | I6: ='두산에너빌리티'!G6 -> 0.264 | M6: =C6/D6 -> 0.34759721
B7: ='한화시스템'!A1 -> 한화시스템 | C7: =F7/G7 -> 0.10079273 | D7: =E7/G7 -> 0.89920727 | E7: ='한화시스템'!D6 -> 6002483.7 | F7: ='한화시스템'!E6 -> 672822.29 | G7: =E7+F7 -> 6675306 | H7: ='한화시스템'!F6 -> 232034.59 | I7: ='한화시스템'!G6 -> 0.231 | M7: =C7/D7 -> 0.11209065
B8: ='LIG넥스원'!A1 -> LIG디펜스앤에어로스페이스 | C8: =F8/G8 -> 0.051813125 | D8: =E8/G8 -> 0.94818687 | E8: ='LIG넥스원'!D6 -> 5405001.3 | F8: ='LIG넥스원'!E6 -> 295353.18 | G8: =E8+F8 -> 5700354.5 | H8: ='LIG넥스원'!F6 -> 276386.04 | I8: ='LIG넥스원'!G6 -> 0.231 | M8: =C8/D8 -> 0.054644424
B11: avg | C11: =AVERAGE(C5:C8) -> 0.13885851 | D11: =AVERAGE(D5:D8) -> 0.86114149 | M11: =AVERAGE(M5:M8) -> 0.17094301
B12: med | C12: =AVERAGE(C6:C9) -> 0.13684812 | D12: =AVERAGE(D6:D9) -> 0.86315188 | M12: =AVERAGE(M6:M9) -> 0.17144409

Sheet peer >>

Sheet 한국한공우주
A1: 한국항공우주
A2: 45777
G4: (단위: 백만)
B5: 주가 | C5: 유통주식수 | D5: 시가총액 | E5: ibd | F5: ltm ebit | G5: tax rate
B6: 75000 | C6: =D22 -> 97475107 | D6: =(B6*C6)/10^6 -> 7310633 | E6: =SUMIF(A:A,E5,C:C)/10^6+(D94+D102)/10^3 -> 1238712 | F6: =(H39+N39-J39)/10^6 -> 239519.23 | G6: =IF(F6<=200, 0.99, IF(F6<=20000, 0.209, IF(F6<=300000, 0.231, 0.264))) -> 0.231
B9: 4. 주식의 총수 등
B12: (기준일 : | C12: 45747 | D12: ) | E12: (단위 : 주, %)
B13: 구 분 | D13: 주식의 종류 | G13: 비고
D14: 보통주 | E14: 우선주 | F14: 합계
B15: Ⅰ. 발행할 주식의 총수 | D15: 200000000 | E15: - | F15: 200000000 | G15: -
B16: Ⅱ. 현재까지 발행한 주식의 총수 | D16: 148907209 | E16: - | F16: 148907209 | G16: -
B17: Ⅲ. 현재까지 감소한 주식의 총수 | D17: 51432102 | E17: - | F17: 51432102 | G17: -
C18: 1. 감자 | D18: 51432102 | E18: - | F18: 51432102 | G18: -
C19: 2. 이익소각 | D19: - | E19: - | F19: - | G19: -
C20: 3. 상환주식의 상환 | D20: - | E20: - | F20: - | G20: -
C21: 4. 기타 | D21: - | E21: - | F21: - | G21: -
B22: Ⅳ. 발행주식의 총수 (Ⅱ-Ⅲ) | D22: 97475107 | E22: - | F22: 97475107 | G22: -
B23: Ⅴ. 자기주식수 | D23: - | E23: - | F23: - | G23: -
B24: Ⅵ. 유통주식수 (Ⅳ-Ⅴ) | D24: 97475107 | E24: - | F24: 97475107 | G24: -
B25: Ⅶ. 자기주식 보유비율 | D25: - | E25: - | F25: - | G25: -
B28: 2-1. 연결 재무상태표 | G28: 2-2. 연결 포괄손익계산서 | M28: 2-2. 연결 포괄손익계산서
B29: 연결 재무상태표 | G29: 연결 포괄손익계산서 | M29: 연결 포괄손익계산서
B30: 제 27 기 1분기말 2025.03.31 현재 | G30: 제 27 기 1분기 2025.01.01 부터 2025.03.31 까지 | M30: 제 26 기 2024.01.01 부터 2024.12.31 까지
B31: 제 26 기말 2024.12.31 현재 | G31: 제 26 기 1분기 2024.01.01 부터 2024.03.31 까지 | M31: 제 25 기 2023.01.01 부터 2023.12.31 까지
B32: (단위 : 원) | G32: (단위 : 원) | M32: 제 24 기 2022.01.01 부터 2022.12.31 까지
C33: 제 27 기 1분기말 | D33: 제 26 기말 | H33: 제 27 기 1분기 | J33: 제 26 기 1분기 | M33: (단위 : 원)
B34: 자산 | H34: 3개월 | I34: 누적 | J34: 3개월 | K34: 누적 | N34: 제 26 기 | O34: 제 25 기 | P34: 제 24 기
B35: 유동자산 | C35: 6133242748971 | D35: 5439008063568 | G35: 수익(매출액) (주26,33,36,37) | H35: 699256592260 | I35: 699256592260 | J35: 739922390124 | K35: 739922390124 | M35: 수익(매출액) (주26,33,36,37) | N35: 3633742105840 | O35: 3819344382446 | P35: 2786888282702
B36: 현금및현금성자산 (주6,35) | C36: 138032136378 | D36: 114716160403 | G36: 매출원가 (주27,33) | H36: 578930842958 | I36: 578930842958 | J36: 642207439792 | K36: 642207439792 | M36: 매출원가 (주27,33) | N36: 3152251662461 | O36: 3355494014353 | P36: 2413060986583
B37: 유동당기손익-공정가치 측정 금융상품 (주5,6,9,35) | C37: 300000000000 | D37: 27131621918 | G37: 매출총이익 | H37: 120325749302 | I37: 120325749302 | J37: 97714950332 | K37: 97714950332 | M37: 매출총이익 | N37: 481490443379 | O37: 463850368093 | P37: 373827296119
B38: 유동매출채권 (주6,7,26,33) | C38: 395719299735 | D38: 398755279903 | G38: 판매비와관리비 (주27,28) | H38: 73512834257 | I38: 73512834257 | J38: 49702958969 | K38: 49702958969 | M38: 판매비와관리비 (주27,28) | N38: 240772132979 | O38: 216339884938 | P38: 232209628801
B39: 유동계약자산 (주7,26) | C39: 620054283361 | D39: 481616109522 | G39: 영업이익(손실) (주36) | H39: 46812915045 | I39: 46812915045 | J39: 48011991363 | K39: 48011991363 | M39: 영업이익(손실) (주36) | N39: 240718310400 | O39: 247510483155 | P39: 141617667318
B40: 기타유동금융자산 (주6,7,33) | C40: 21653458791 | D40: 22371366814 | G40: 기타이익 (주29) | H40: 438466476 | I40: 438466476 | J40: 503545853 | K40: 503545853 | M40: 기타이익 (주29,33) | N40: 8943702027 | O40: 16901628950 | P40: 10690416573
B41: 유동재고자산 (주8) | C41: 2718905396687 | D41: 2359034707814 | G41: 기타손실 (주29) | H41: 581091315 | I41: 581091315 | J41: 694839418 | K41: 694839418 | M41: 기타손실 (주29,33) | N41: 27300056509 | O41: 20906948393 | P41: 6871167952
B42: 당기법인세자산 (주31) | C42: 62362000 | D42: 53939720 | G42: 금융수익 (주6,30,33) | H42: 55198453540 | I42: 55198453540 | J42: 43618761478 | K42: 43618761478 | M42: 금융수익 (주6,30,33) | N42: 121109213680 | O42: 112453943443 | P42: 109675065480
B43: 기타유동자산 (주14,33) | C43: 1938815812019 | D43: 2035328877474 | G43: 금융원가 (주6,30) | H43: 65183983326 | I43: 65183983326 | J43: 45064043382 | K43: 45064043382 | M43: 금융원가 (주6,30) | N43: 143909460657 | O43: 87591601007 | P43: 132310966928
B44: 비유동자산 | C44: 2600123288969 | D44: 2586530345825 | G44: 지분법손실 (주10) | H44: 976509784 | I44: 976509784 | J44: 946863349 | K44: 946863349 | M44: 지분법이익 (주10) | O44: 1369167843 | P44: 1334591136
B45: 비유동당기손익-공정가치 측정 금융상품 (주5,6,9) | C45: 79626906529 | D45: 79655609179 | G45: 법인세차감전순이익 | H45: 35708250636 | I45: 35708250636 | J45: 45428552545 | K45: 45428552545 | M45: 지분법손실 (주10) | N45: 2455312616 | O45: 1020953512 | P45: 2013675671
B46: 비유동매출채권 (주6,7,26) | C46: 29580273545 | D46: 29511304701 | G46: 법인세비용 (주31) | H46: 6544179205 | I46: 6544179205 | J46: 10202220761 | K46: 10202220761 | M46: 법인세차감전순이익 | N46: 197106396325 | O46: 268715720479 | P46: 122121929956
B47: 기타비유동금융자산 (주4,6,7,33) | C47: 8281520193 | D47: 9200977948 | G47: 당기순이익 | H47: 29164071431 | I47: 29164071431 | J47: 35226331784 | K47: 35226331784 | M47: 법인세비용 (주31) | N47: 26210985348 | O47: 47314600584 | P47: 6202534236
B48: 종속기업, 공동기업과 관계기업에 대한 투자자산 (주10,33) | C48: 13560565574 | D48: 14537075358 | G48: 기타포괄손익 | H48: -4216206 | I48: -4216206 | J48: 95399502 | K48: 95399502 | M48: 당기순이익 | N48: 170895410977 | O48: 221401119895 | P48: 115919395720
B49: 유형자산 (주11,13) | C49: 940358257642 | D49: 912525958117 | G49: 당기손익으로 재분류될 수 있는 항목(세후기타포괄손익) | H49: -4216206 | I49: -4216206 | J49: 95399502 | K49: 95399502 | M49: 기타포괄손익 | N49: -14921492633 | O49: -30308651734 | P49: 59348444108
B50: 무형자산 (주12) | C50: 870842674135 | D50: 845689955229 | G50: 해외사업환산외환차이 | H50: -4216206 | I50: -4216206 | J50: 66634688 | K50: 66634688 | M50: 당기손익으로 재분류되지 않는항목(세후기타포괄손익) | N50: -14977472233 | O50: -30431650836 | P50: 59267549731
B51: 이연법인세자산 (주31) | C51: 328496186182 | D51: 334408365983 | G51: 지분법자본변동 | J51: 28764814 | K51: 28764814 | M51: 확정급여제도의 재측정손익(세전기타포괄손익) (주19) | N51: -19437312039 | O51: -39516263416 | P51: 77771390545
B52: 기타비유동자산 (주14,33) | C52: 329376905169 | D52: 361001099310 | G52: 총포괄손익 | H52: 29159855225 | I52: 29159855225 | J52: 35321731286 | K52: 35321731286 | M52: 기타포괄손익관련 법인세효과 (주31) | N52: 4459839806 | O52: 9084612580 | P52: -18503840814
B53: 자산총계 | C53: 8733366037940 | D53: 8025538409393 | G53: 당기순이익의 귀속 | M53: 당기손익으로 재분류될 수 있는 항목(세후기타포괄손익) | N53: 55979600 | O53: 122999102 | P53: 80894377
B54: 부채 | G54: 지배기업의 소유주에게 귀속되는 당기순이익 | H54: 30064693944 | I54: 30064693944 | J54: 36625831621 | K54: 36625831621 | M54: 해외사업환산외환차이 | N54: 210381674 | O54: 20944688 | P54: 74021534
B55: 유동부채 | C55: 5163350963119 | D55: 4914742846130 | G55: 비지배지분에 귀속되는 당기순이익 | H55: -900622513 | I55: -900622513 | J55: -1399499837 | K55: -1399499837 | M55: 지분법자본변동 (주10) | N55: -154402074 | O55: 102054414 | P55: 6872843
B56: 유동매입채무 (주6,15,33) | C56: 400012461457 | D56: 503924820654 | G56: 포괄손익의 귀속 | M56: 총포괄손익 | N56: 155973918344 | O56: 191092468161 | P56: 175267839828
B57: 기타유동금융부채 (주6,13,15,32,33) | C57: 454289390541 | D57: 455034586958 | G57: 포괄손익, 지배기업의 소유주에게 귀속되는 지분 | H57: 30060477738 | I57: 30060477738 | J57: 36721231123 | K57: 36721231123 | M57: 당기순이익의 귀속
B58: 유동계약부채 (주18,26) | C58: 1923877498591 | D58: 1790653761352 | G58: 포괄손익, 비지배지분 | H58: -900622513 | I58: -900622513 | J58: -1399499837 | K58: -1399499837 | M58: 지배기업의 소유주에게 귀속되는 당기순이익 | N58: 172075960913 | O58: 224022359335 | P58: 118462749084
A59: ibd | B59: 단기차입금 (주6,16,32,35) | C59: 101500000000 | D59: 413870080000 | G59: 주당이익 | M59: 비지배지분에 귀속되는 당기순이익 | N59: -1180549936 | O59: -2621239440 | P59: -2543353364
A60: ibd | B60: 유동성장기차입금 (주6,16,32,35) | C60: 25940002454 | D60: 29099312594 | G60: 기본주당이익 (단위 : 원) (주25) | H60: 308 | I60: 308 | J60: 376 | K60: 376 | M60: 포괄손익의 귀속
B61: 당기법인세부채 (주31) | C61: 21825383229 | D61: 37150836166 | G61: 희석주당이익 (단위 : 원) (주25) | H61: 308 | I61: 308 | J61: 376 | K61: 376 | M61: 포괄손익, 지배기업의 소유주에게 귀속되는 지분 | N61: 157181842930 | O61: 193979072885 | P61: 177872523074
B62: 유동충당부채 (주20,26,34) | C62: 55516361257 | D62: 64007068063 | M62: 포괄손익, 비지배지분 | N62: -1207924586 | O62: -2886604724 | P62: -2604683246
B63: 기타 유동부채 (주17,18) | C63: 2180389865590 | D63: 1621002380343 | M63: 주당이익
B64: 비유동부채 | C64: 1862415890975 | D64: 1383618681142 | M64: 기본주당이익 (단위 : 원) (주25) | N64: 1765 | O64: 2298 | P64: 1215
A65: ibd | B65: 장기차입금 (주6,16,32,35) | C65: 39471763413 | D65: 43462002449 | M65: 희석주당이익 (단위 : 원) (주25) | N65: 1765 | O65: 2298 | P65: 1215
A66: ibd | B66: 사채 (주6,16,32,35) | C66: 1048332985812 | D66: 549289349481
B67: 기타비유동금융부채 (주6,13,15,32) | C67: 226715538670 | D67: 238053665761
B68: 순확정급여부채 (주19) | C68: 443932349786 | D68: 452225263324
B69: 비유동충당부채 (주20,26,34) | C69: 56614752452 | D69: 54993625449
B70: 기타 비유동 부채 (주17,18) | C70: 47348500842 | D70: 45594774678
B71: 부채총계 | C71: 7025766854094 | D71: 6298361527272
B72: 자본
B73: 지배기업의 소유주에게 귀속되는 자본 | C73: 1687180167272 | D73: 1705857243034
B74: 자본금 (주1,22) | C74: 487375535000 | D74: 487375535000
B75: 주식발행초과금 | C75: 124077485927 | D75: 124077485927
B76: 이익잉여금 (주23) | C76: 1092341286989 | D76: 1111014146545
B77: 기타자본항목 (주24) | C77: -16614140644 | D77: -16609924438
B78: 비지배지분 | C78: 20419016574 | D78: 21319639087
B79: 자본총계 | C79: 1707599183846 | D79: 1727176882121
B80: 자본과부채총계 | C80: 8733366037940 | D80: 8025538409393
C81: 825442446 | D81: 688613752
C82: -37942864 | D82: -35892634
B83: 자본총계 | C83: 2147329022 | D83: 2009085189
B84: 부채와자본총계 | C84: 5244442521 | D84: 5285394740
B86: 15.매입채무 및 기타금융부채
B88: 매입채무 및 기타채무
B89: 당분기말 | C89: (단위 : 천원)
D90: 공시금액
B91: 매입채무 및 기타유동채무
B92: 매입채무 및 기타유동채무 | C92: 매입채무 | D92: 405118920
C93: 단기미지급금 | D93: 91069677
C94: 유동 리스부채 | D94: 5155517
C95: 단기미지급비용 (*) | D95: 279077989
C96: 현재가치할인차금, 단기미지급비용 | D96: -3668675
C97: 미지급 배당금 | D97: 48737554
C98: 소계 | D98: 825490982
B99: 매입채무 및 기타비유동채무
B100: 매입채무 및 기타비유동채무 | C100: 장기미지급금, 총액 | D100: 102965021
C101: 현재가치할인차금, 장기미지급금 | D101: -548094
C102: 비유동 리스부채 | D102: 18311700
C103: 장기미지급비용, 총액 | D103: 88108363
C104: 현재가치할인차금, 장기미지급비용 | D104: -578280
C105: 소계 | D105: 208258710
B106: 합계 | D106: 1033749692

Sheet 두산에너빌리티
A1: 두산에너빌리티
A2: 45777
G4: (단위: 백만) | I4: *NOTE
B5: 주가 | C5: 유통주식수 | D5: 시가총액 | E5: ibd | F5: ltm ebit | G5: tax rate | I5: 분기보고서 내 주식의 총수 기재하지 않아 직전 사업보고서 사용
B6: 28950 | C6: =D32 -> 640465168 | D6: =(B6*C6)/10^6 -> 18541467 | E6: =SUMIF(A:A,E5,C:C) -> 6444962 | F6: =(H58+N58-J58) -> 802004 | G6: =IF(F6<=200, 0.99, IF(F6<=20000, 0.209, IF(F6<=300000, 0.231, 0.264))) -> 0.264
B9: 4. 주식의 총수 등
B11: 가. 주식의 총수 현황
B12: 당사의 정관에 의해 발행할 주식의 총수는 2,000,000,000주입니다.
B13: 당기말까지 당사가 발행한 주식의 총수는 655,764,686주이며, 이 중 보통주
B14: 2,000,000주를 감자하고 상환전환우선주(RCPS) 299,330주가 보통주로
B15: 전환되었으며, 상환전환 우선주 (RCPS) 12,904,210주는 전량 소각하여,
B16: 당기말 현재 발행주식의 총수는 640,561,146주(보통주)입니다.
B17: 당기말 현재 유가증권시장에 상장된 주식수는 640,561,146주이며,
B18: 유통주식수는 자기주식 95,978주를 제외한 640,465,168주입니다.
B20: (기준일 : | C20: 45657 | D20: ) | E20: (단위 : 주, %)
B21: 구 분 | D21: 주식의 종류 | G21: 비고
D22: 보통주 | E22: 우선주 | F22: 합계
B23: Ⅰ. 발행할 주식의 총수 | D23: 2000000000 | E23: - | F23: 2000000000 | G23: -
B24: Ⅱ. 현재까지 발행한 주식의 총수 | D24: 642561146 | E24: 13203540 | F24: 655764686 | G24: -
B25: Ⅲ. 현재까지 감소한 주식의 총수 | D25: 2000000 | E25: 13203540 | F25: 15203540 | G25: -
C26: 1. 감자 | D26: 2000000 | E26: - | F26: 2000000 | G26: -
C27: 2. 이익소각 | D27: - | E27: - | F27: - | G27: -
C28: 3. 상환주식의 상환 | D28: - | E28: 12904210 | F28: 12904210 | G28: 자기주식 취득 후 소각
C29: 4. 기타 | D29: - | E29: 299330 | F29: 299330 | G29: 상환전환우선주의 전환
B30: Ⅳ. 발행주식의 총수 (Ⅱ-Ⅲ) | D30: 640561146 | E30: - | F30: 640561146 | G30: -
B31: Ⅴ. 자기주식수 | D31: 95978 | E31: - | F31: 95978 | G31: 분할합병 및 포괄적 주식교환 신주/단주취득
B32: Ⅵ. 유통주식수 (Ⅳ-Ⅴ) | D32: 640465168 | E32: - | F32: 640465168 | G32: -
B33: Ⅶ. 자기주식 보유비율 | D33: - | E33: - | F33: - | G33: -
B34: ※ 최근 5년간 주식 수의 주요 변동내역은 아래와 같습니다. - 2020년 02월 06일자로 보통주 44,102,845주를 유상증자(제3자배정)하였습니다. - 2020년 03월 10일자로 두산건설㈜의 상장폐지에 따른 포괄적 주식 교환을 위하여 보통주 6,891,058주를 신주 발행하였고, 발행과정에서 단수주 취득으로 자사주 5,850주를 취득하였습니다. - 2020년 12월 12일자로 보통주 121,495,330주를 유상증자(일반공모)하였습니다. - 2021년 04월 02일자로 두산퓨얼셀㈜ 현물출자로 보통주 47,843,956주를 유상증자(제3자배정)하였습니다. - 2021년 07월 01일자로 두산인프라코어㈜의 투자사업부문 합병에 따라 보통주 83,399,437주가 신규 발행하였고, 분할합병 발행과정에서 단수주 및 매수청구권 행사로 자사주 81,649주를 취득하였습니다. - 2022년 02월 19일자로 보통주 82,872,900주를 유상증자(구주주배정)하였습니다. - 2021년 07월 01일자로 발행한 신주인수권부사채의 신주인수권증권(2WR) 행사로 2022.06.30일까지 보통주 12,566,852주가 신규 발행되었습니다. - 2022년 07월 01일자로 발행한 신주인수권부사채의 신주인수권증권(2WR) 행사로 보통주 3,014,983주가 신규 발행되었으며, 신주인수권부사채의 신주인수권증권(2WR)의 행사기간이 종료되었습니다. - 2023년 03월 29일자로 제59회, 제60회 전환사채가 전부전환이 되어 보통주 2,253,113주를 신주발행하였습니다.
B39: 2-1. 연결 재무상태표
B40: 연결 재무상태표
B41: 제 63 기 1분기말 2025.03.31 현재
B42: 제 62 기말 2024.12.31 현재
B43: (단위 : 백만원)
C44: 제 63 기 1분기말 | D44: 제 62 기말
B45: 자산
B46: 유동자산 | C46: 10508418 | D46: 10049022
B47: 현금및현금성자산 | C47: 2609660 | D47: 2898298 | G47: 2-2. 연결 손익계산서 | M47: 2-2. 연결 손익계산서
B48: 단기금융상품 | C48: 151970 | D48: 143577 | G48: 연결 손익계산서 | M48: 연결 손익계산서
B49: 단기투자증권 | C49: 0 | D49: 0 | G49: 제 63 기 1분기 2025.01.01 부터 2025.03.31 까지 | M49: 제 62 기 2024.01.01 부터 2024.12.31 까지
B50: 매출채권 | C50: 1571054 | D50: 1290275 | G50: 제 62 기 1분기 2024.01.01 부터 2024.03.31 까지 | M50: 제 61 기 2023.01.01 부터 2023.12.31 까지
B51: 미청구공사 | C51: 1785013 | D51: 1594506 | G51: (단위 : 백만원) | M51: 제 60 기 2022.01.01 부터 2022.12.31 까지
B52: 미수금 | C52: 419182 | D52: 477472 | H52: 제 63 기 1분기 | J52: 제 62 기 1분기 | M52: (단위 : 백만원)
B53: 선급금 | C53: 377116 | D53: 360750 | H53: 3개월 | I53: 누적 | J53: 3개월 | K53: 누적 | N53: 제 62 기 | O53: 제 61 기 | P53: 제 60 기
B54: 선급비용 | C54: 176592 | D54: 131249 | G54: 매출액 | H54: 3748574 | I54: 3748574 | J54: 4097867 | K54: 4097867 | M54: 매출액 | N54: 16233055 | O54: 17589888 | P54: 15421058
B55: 단기대여금 | C55: 28796 | D55: 27611 | G55: 매출원가 | H55: 3150914 | I55: 3150914 | J55: 3350759 | K55: 3350759 | M55: 매출원가 | N55: 13503336 | O55: 14572887 | P55: 12865181
B56: 파생상품평가자산 | C56: 17712 | D56: 37905 | G56: 매출총이익 | H56: 597660 | I56: 597660 | J56: 747108 | K56: 747108 | M56: 매출총이익 | N56: 2729719 | O56: 3017001 | P56: 2555877
B57: 확정계약자산 | C57: 108750 | D57: 114250 | G57: 판매비와관리비 | H57: 455185 | I57: 455185 | J57: 389037 | K57: 389037 | M57: 판매비와관리비 | N57: 1712119 | O57: 1549683 | P57: 1449756
B58: 재고자산 | C58: 3037819 | D58: 2733933 | G58: 영업이익 | H58: 142475 | I58: 142475 | J58: 358071 | K58: 358071 | M58: 영업이익 | N58: 1017600 | O58: 1467318 | P58: 1106121
B59: 매각예정자산 | C59: 1291 | D59: 1506 | G59: 금융손익 | H59: -79445 | I59: -79445 | J59: -14695 | K59: -14695 | M59: 금융손익 | N59: -181252 | O59: -267951 | P59: -477603
B60: 기타유동자산 | C60: 223463 | D60: 237690 | G60: 금융수익 | H60: 269121 | I60: 269121 | J60: 349958 | K60: 349958 | M60: 금융수익 | N60: 1155804 | O60: 595111 | P60: 747016
B61: 비유동자산 | C61: 16388575 | D61: 16265813 | G61: 금융비용 | H61: 348566 | I61: 348566 | J61: 364653 | K61: 364653 | M61: 금융비용 | N61: 1337056 | O61: 863062 | P61: 1224619
B62: 장기금융상품 | C62: 25079 | D62: 25117 | G62: 기타영업외손익 | H62: -34702 | I62: -34702 | J62: 18932 | K62: 18932 | M62: 기타영업외손익 | N62: -199053 | O62: -422197 | P62: -584512
B63: 장기투자증권 | C63: 454764 | D63: 436601 | G63: 기타영업외수익 | H63: 4624 | I63: 4624 | J63: 36346 | K63: 36346 | M63: 기타영업외수익 | N63: 143768 | O63: 49304 | P63: 158644
B64: 관계기업 및 공동기업투자 | C64: 348456 | D64: 347660 | G64: 기타영업외비용 | H64: 39326 | I64: 39326 | J64: 17414 | K64: 17414 | M64: 기타영업외비용 | N64: 342821 | O64: 471501 | P64: 743156
B65: 장기대여금 | C65: 148235 | D65: 171691 | G65: 지분법이익 | H65: 1879 | I65: 1879 | J65: 6530 | K65: 6530 | M65: 지분법이익 | N65: 20484 | O65: -38688 | P65: -230486
... B67: 무형자산 | C67: 8515804 | D67: 8397290 | G67: 법인세비용 | H67: 51364 | I67: 51364 | J67: 107786 | K67: 107786 | M67: 법인세비용 | N67: 263090 | O67: 220960 | P67: 146997
B68: 투자부동산 | C68: 226689 | D68: 228288 | G68: 분기순이익(손실) | H68: -21157 | I68: -21157 | J68: 261052 | K68: 261052 | M68: 계속영업이익(손실) | P68: -333477
B69: 파생상품평가자산 | C69: 25983 | D69: 17772 | G69: 분기순이익의 귀속 | M69: 중단영업이익(손실) | P69: -119673
B70: 확정계약자산 | C70: 10979 | D70: 13537 | G70: 지배기업 소유주지분 | H70: -68860 | I70: -68860 | J70: 144160 | K70: 144160 | M70: 당기순이익 | N70: 394689 | O70: 517522 | P70: -453150
B71: 보증금 | C71: 150839 | D71: 169612 | G71: 비지배지분 | H71: 47703 | I71: 47703 | J71: 116892 | K71: 116892 | M71: 당기순이익의 귀속
B72: 이연법인세자산 | C72: 557815 | D72: 556161 | G72: 지배기업 소유주지분 주당손익 | M72: 지배기업 소유주지분 | N72: 111365 | O72: 55598 | P72: -772492
B73: 순확정급여자산 | C73: 14315 | D73: 16927 | G73: 기본주당이익 (단위 : 원) | H73: -108 | I73: -108 | J73: 225 | K73: 225 | M73: 비지배지분 | N73: 283324 | O73: 461924 | P73: 319342
B74: 기타비유동자산 | C74: 192681 | D74: 182108 | G74: 희석주당이익 (단위 : 원) | H74: -108 | I74: -108 | J74: 225 | K74: 225 | M74: 지배기업 소유주지분 주당손익
B75: 자산총계 | C75: 26896993 | D75: 26314835 | M75: 기본주당이익 (단위 : 원) | N75: 174 | O75: 87 | P75: -1249
B76: 부채 | M76: 계속영업기본주당이익(손실) (단위 : 원) | P76: -1056
B77: 유동부채 | C77: 9510646 | D77: 8945820 | M77: 중단영업기본주당이익(손실) (단위 : 원) | P77: -193
B78: 매입채무 | C78: 2443802 | D78: 2220935 | M78: 희석주당이익 (단위 : 원) | N78: 174 | O78: 87 | P78: -1249
A79: ibd | B79: 단기차입금 | C79: 2427445 | D79: 2141257 | M79: 계속영업희석주당이익(손실) (단위 : 원) | P79: -1056
B80: 미지급금 | C80: 234902 | D80: 318589 | M80: 중단영업희석주당이익(손실) (단위 : 원) | P80: -193
B81: 선수금 | C81: 68153 | D81: 50165
B82: 초과청구공사 | C82: 1822657 | D82: 1800050
B83: 예수금 | C83: 121342 | D83: 96808
B84: 미지급비용 | C84: 972562 | D84: 1026238
B85: 당기법인세부채 | C85: 112208 | D85: 93490
B86: 미지급배당금 | C86: 42071
A87: ibd | B87: 유동성장기부채 | C87: 568524 | D87: 398220
B88: 파생상품평가부채 | C88: 133039 | D88: 214127
B89: 확정계약부채 | C89: 2796 | D89: 5893
B90: 충당부채 | C90: 236405 | D90: 241923
A91: ibd | B91: 유동 리스부채 | C91: 101479 | D91: 102853
A92: ibd | B92: 판매후리스부채 | C92: 15773 | D92: 18331
B93: 기타 유동부채 | C93: 207488 | D93: 216941
B94: 비유동부채 | C94: 5643218 | D94: 5707923
A95: ibd | B95: 사채 | C95: 818317 | D95: 906758
A96: ibd | B96: 장기차입금 | C96: 2513424 | D96: 2434534
B97: 장기유동화채무 | C97: 11085 | D97: 19392
B98: 장기미지급금 | C98: 12016 | D98: 11189
B99: 순확정급여부채 | C99: 573151 | D99: 570726
B100: 예수보증금 | C100: 247104 | D100: 277852
B101: 파생상품평가부채 | C101: 16627 | D101: 30217
B102: 확정계약부채 | C102: 4173 | D102: 2457
B103: 이연법인세부채 | C103: 494409 | D103: 510165
B104: 충당부채 | C104: 365578 | D104: 364830
B105: 비유동 리스부채 | C105: 288369 | D105: 302032
B106: 비유동판매후리스부채 | C106: 52713 | D106: 48234
B107: 기타비유동부채 | C107: 246252 | D107: 229537
B108: 부채총계 | C108: 15153864 | D108: 14653743
B109: 자본
B110: 지배회사 소유주지분 | C110: 7603719 | D110: 7496562
...

Sheet 한화시스템
A1: 한화시스템
A2: 45777
G4: (단위: 백만) | I4: *NOTE
B5: 주가 | C5: 유통주식수 | D5: 시가총액 | E5: ibd | F5: ltm ebit | G5: tax rate | I5: 분기보고서 내 주식의 총수 기재하지 않아 직전 사업보고서 사용
B6: 32100 | C6: =D24 -> 186993261 | D6: =B6*C6/10^6 -> 6002483.7 | E6: =SUMIF(A:A,E5,E:E)/10^3 -> 672822.29 | F6: =(H41+N40-J41)/10^6 -> 232034.59 | G6: =IF(F6<=200, 0.99, IF(F6<=20000, 0.209, IF(F6<=300000, 0.231, 0.264))) -> 0.231
B9: 4. 주식의 총수 등
B11: 가. 주식의 총수 현황
B12: (기준일 : | C12: 45657 | D12: ) | E12: (단위 : 주, %)
B13: 구 분 | D13: 주식의 종류 | G13: 비고
D14: 보통주 | E14: 종류주식 | F14: 합계
B15: Ⅰ. 발행할 주식의 총수 | D15: 500000000 | E15: - | F15: 500000000 | G15: -
B16: Ⅱ. 현재까지 발행한 주식의 총수 | D16: 188919389 | E16: - | F16: 188919389 | G16: -
B17: Ⅲ. 현재까지 감소한 주식의 총수 | D17: - | E17: - | F17: - | G17: -
C18: 1. 감자 | D18: - | E18: - | F18: - | G18: -
C19: 2. 이익소각 | D19: - | E19: - | F19: - | G19: -
C20: 3. 상환주식의 상환 | D20: - | E20: - | F20: - | G20: -
C21: 4. 기타 | D21: - | E21: - | F21: - | G21: -
B22: Ⅳ. 발행주식의 총수 (Ⅱ-Ⅲ) | D22: 188919389 | E22: - | F22: 188919389 | G22: -
B23: Ⅴ. 자기주식수 | D23: 1926128 | E23: - | F23: 1926128 | G23: -
B24: Ⅵ. 유통주식수 (Ⅳ-Ⅴ) | D24: 186993261 | E24: - | F24: 186993261 | G24: -
B25: Ⅶ. 자기주식 보유비율 | D25: 1.02 | E25: - | F25: 1.02 | G25: -
B30: 2-1. 연결 재무상태표 | G30: 2-2. 연결 포괄손익계산서 | M30: 연결 포괄손익계산서
B31: 연결 재무상태표 | G31: 연결 포괄손익계산서 | M31: 제 25 기 2024.01.01 부터 2024.12.31 까지
B32: 제 26 기 1분기말 2025.03.31 현재 | G32: 제 26 기 1분기 2025.01.01 부터 2025.03.31 까지 | M32: 제 24 기 2023.01.01 부터 2023.12.31 까지
B33: 제 25 기말 2024.12.31 현재 | G33: 제 25 기 1분기 2024.01.01 부터 2024.03.31 까지 | M33: 제 23 기 2022.01.01 부터 2022.12.31 까지
B34: (단위 : 원) | G34: (단위 : 원) | M34: (단위 : 원)
C35: 제 26 기 1분기말 | D35: 제 25 기말 | H35: 제 26 기 1분기 | J35: 제 25 기 1분기 | N35: 제 25 기 | O35: 제 24 기 | P35: 제 23 기
B36: 자산 | H36: 3개월 | I36: 누적 | J36: 3개월 | K36: 누적 | M36: 매출액 | N36: 2803686058274 | O36: 2452494865652 | P36: 2187382784077
B37: 유동자산 | C37: 2418286851683 | D37: 2286147317733 | G37: 매출액 | H37: 690100705524 | I37: 690100705524 | J37: 544171697458 | K37: 544171697458 | M37: 매출원가 | N37: 2387893541859 | O37: 2148350487679 | P37: 1932111383713
B38: 현금및현금성자산 | C38: 240375736929 | D38: 199842738640 | G38: 매출원가 | H38: 578635666718 | I38: 578635666718 | J38: 458017757393 | K38: 458017757393 | M38: 매출총이익 | N38: 415792516415 | O38: 304144377973 | P38: 255271400364
B39: 매출채권 및 기타유동채권 | C39: 251595804206 | D39: 309758809799 | G39: 매출총이익 | H39: 111465038806 | I39: 111465038806 | J39: 86153940065 | K39: 86153940065 | M39: 판매비와관리비 | N39: 196447218733 | O39: 181569236969 | P39: 192967772698
B40: 기타유동금융자산 | C40: 107170965006 | D40: 124138313927 | G40: 판매비와관리비 | H40: 53300686503 | I40: 53300686503 | J40: 40678878429 | K40: 40678878429 | M40: 영업이익(손실) | N40: 219345297682 | O40: 122575141004 | P40: 62303627666
B41: 기타유동자산 | C41: 1113491159898 | D41: 1025685101781 | G41: 영업이익(손실) | H41: 58164352303 | I41: 58164352303 | J41: 45475061636 | K41: 45475061636 | M41: 기타이익 | N41: 471189148580 | O41: 381777493578 | P41: 8080822090
B42: 유동재고자산 | C42: 705653185644 | D42: 610096270571 | G42: 기타이익 | H42: 39556431954 | I42: 39556431954 | J42: 43736584704 | K42: 43736584704 | M42: 기타손실 | N42: 105181510953 | O42: 44361931795 | P42: 84898552636
B43: 매각예정 또는 소유주에 대한 분배예정으로 분류된 비유동자산이나 처분자산집단 | C43: 0 | D43: 16626083015 | G43: 기타손실 | H43: 62821422844 | I43: 62821422844 | J43: 1166000265 | K43: 1166000265 | M43: 금융수익 | N43: 48063606585 | O43: 31524196161 | P43: 35051390040
B44: 비유동자산 | C44: 4794325951780 | D44: 3437862797985 | G44: 금융수익 | H44: 16395091333 | I44: 16395091333 | J44: 8636267088 | K44: 8636267088 | M44: 금융원가 | N44: 39407264646 | O44: 17408047107 | P44: 11985829095
B45: 비유동당기손익인식금융자산 | C45: 395796314696 | D45: 366532174827 | G45: 금융원가 | H45: 10108289449 | I45: 10108289449 | J45: 5106319360 | K45: 5106319360 | M45: 지분법손익 | N45: -12596342874 | O45: -30247728517 | P45: -26708314516
B46: 기타포괄손익-공정가치 측정 비유동금융자산 | C46: 2770648647001 | D46: 1438036682961 | G46: 지분법손익 | H46: -1914582266 | I46: -1914582266 | J46: -22271994223 | K46: -22271994223 | M46: 법인세비용차감전순이익(손실) | N46: 581412934374 | O46: 443859123324 | P46: -18156856451
B47: 기타비유동금융자산 | C47: 74398385546 | D47: 74055892315 | G47: 법인세비용차감전순이익(손실) | H47: 39271581031 | I47: 39271581031 | J47: 69303599580 | K47: 69303599580 | M47: 법인세비용(수익) | N47: 104258545307 | O47: 57411211791 | P47: 23735116786
B48: 관계기업에 대한 투자자산 | C48: 19301342014 | D48: 24551532882 | G48: 법인세비용(수익) | H48: 5838641620 | I48: 5838641620 | J48: 9122826801 | K48: 9122826801 | M48: 계속영업이익(손실) | N48: 477154389067 | O48: 386447911533 | P48: -41891973237
... B50: 사용권자산 | C50: 146705809980 | D50: 154215135942 | G50: 중단영업이익(손실) | H50: 7536906022 | I50: 7536906022 | J50: -9857509426 | K50: -9857509426 | M50: 당기순이익(손실) | N50: 445378843124 | O50: 343083288939 | P50: -80760193717
B51: 무형자산 | C51: 759170725628 | D51: 762189505792 | G51: 당기순이익(손실) | H51: 40969845433 | I51: 40969845433 | J51: 50323263353 | K51: 50323263353 | M51: 당기순이익(손실)의 귀속
B52: 기타비유동자산 | C52: 7208256173 | D52: 6739693964 | G52: 당기순이익(손실)의 귀속 | M52: 지배기업의 소유주에게 귀속되는 당기순이익(손실) | N52: 454300056693 | O52: 349221289086 | P52: -76555797899
B53: 이연법인세자산 | C53: 14077558420 | D53: 41589408570 | G53: 지배기업의 소유주에게 귀속되는 당기순이익(손실) | H53: 37834899054 | I53: 37834899054 | J53: 51805059317 | K53: 51805059317 | M53: 비지배지분에 귀속되는 당기순이익(손실) | N53: -8921213569 | O53: -6138000147 | P53: -4204395818
B54: 자산총계 | C54: 7212612803463 | D54: 5724010115718 | G54: 비지배지분에 귀속되는 당기순이익(손실) | H54: 3134946379 | I54: 3134946379 | J54: -1481795964 | K54: -1481795964 | M54: 기타포괄손익 | N54: -34573519586 | O54: -176400561422 | P54: -116331712059
B55: 부채 | G55: 기타포괄손익 | H55: 892581403766 | I55: 892581403766 | J55: 13397657382 | K55: 13397657382 | M55: 당기손익으로 재분류될 수 있는 항목(세후기타포괄손익) | N55: 75988073348 | O55: 8508028710 | P55: -196325513
B56: 유동부채 | C56: 2897194696019 | D56: 2677051475212 | G56: 당기손익으로 재분류될 수 있는 항목(세후기타포괄손익) | H56: 5670898970 | I56: 5670898970 | J56: 23365872487 | K56: 23365872487 | M56: 해외사업장환산외환차이(세후기타포괄손익) | N56: 61468177044 | O56: 22258528105 | P56: -1004443716
B57: 매입채무 및 기타유동채무 | C57: 345784374156 | D57: 250001338211 | G57: 해외사업장환산외환차이(세후기타포괄손익) | H57: 5783797790 | I57: 5783797790 | J57: 20345106286 | K57: 20345106286 | M57: 지분법 적용대상 관계기업과 공동기업의 기타포괄손익에 대한 지분(세후기타포괄손익) | N57: 14519896304 | O57: -13750499395 | P57: 808118203
B58: 유동 차입금 및 사채 | C58: 244634769303 | D58: 79955187062 | G58: 지분법 적용대상 관계기업과 공동기업의 기타포괄손익에 대한 지분(세후기타포괄손익) | H58: -112898820 | I58: -112898820 | J58: 3020766201 | K58: 3020766201 | M58: 당기손익으로 재분류되지 않는항목(세후기타포괄손익) | N58: -110561592934 | O58: -184908590132 | P58: -116135386546
B59: 기타유동금융부채 | C59: 124861044912 | D59: 195531569300 | G59: 당기손익으로 재분류되지 않는항목(세후기타포괄손익) | H59: 886910504796 | I59: 886910504796 | J59: -9968215105 | K59: -9968215105 | M59: 세후기타포괄손익, 지분상품에 대한 투자자산 | N59: -94453681508 | O59: -143222483280 | P59: -114809170079
B60: 기타 유동부채 | C60: 2090673756908 | D60: 2027772105965 | G60: 세후기타포괄손익, 지분상품에 대한 투자자산 | H60: 886910504796 | I60: 886910504796 | J60: -9955982547 | K60: -9955982547 | M60: 확정급여제도의 재측정손익(세후기타포괄손익) | N60: -16107911426 | O60: -41686106852 | P60: -1326216467
B61: 유동충당부채 | C61: 69394050223 | D61: 83709542233 | G61: 확정급여제도의 재측정손익(세후기타포괄손익) | H61: 0 | J61: -12232558 | K61: -12232558 | M61: 총포괄손익 | N61: 410805323538 | O61: 166682727517 | P61: -197091905776
B62: 당기법인세부채 | C62: 21846700517 | D62: 37318840494 | G62: 총포괄손익 | H62: 933551249199 | I62: 933551249199 | J62: 63720920735 | K62: 63720920735 | M62: 포괄손익의 귀속
B63: 매각예정부채 | C63: 0 | D63: 2762891947 | G63: 포괄손익의 귀속 | M63: 포괄손익, 지배기업의 소유주에게 귀속되는 지분 | N63: 419715332564 | O63: 172915366496 | P63: -192821776262
B64: 비유동부채 | C64: 902350009454 | D64: 630541745050 | G64: 포괄손익, 지배기업의 소유주에게 귀속되는 지분 | H64: 933043262566 | I64: 933043262566 | J64: 65173185248 | K64: 65173185248 | M64: 포괄손익, 비지배지분 | N64: -8910009026 | O64: -6232638979 | P64: -4270129514
B65: 비유동 차입금 및 사채 | C65: 290667017059 | D65: 249276736308 | G65: 포괄손익, 비지배지분 | H65: 507986633 | I65: 507986633 | J65: -1452264513 | K65: -1452264513 | M65: 주당이익
B66: 기타비유동금융부채 | C66: 136787938086 | D66: 132646054557 | G66: 주당이익 | M66: 계속영업기본주당이익(손실) (단위 : 원) | N66: 2591 | O66: 2092 | P66: -224
B67: 퇴직급여부채 | C67: 214431997763 | D67: 207330078337 | G67: 계속영업기본주당이익(손실) (단위 : 원) | H67: 159 | I67: 159 | J67: 321 | K67: 321 | M67: 계속영업희석주당이익(손실) (단위 : 원) | N67: 2589 | O67: 2092 | P67: -224
B68: 비유동충당부채 | C68: 31211507909 | D68: 30505071667 | G68: 계속영업희석주당이익(손실) (단위 : 원) | H68: 159 | I68: 159 | J68: 321 | K68: 321 | M68: 중단영업기본주당이익(손실) (단위 : 원) | N68: -169 | O68: -228 | P68: -185
B69: 이연법인세부채 | C69: 229251548637 | D69: 10783804181 | G69: 중단영업기본주당이익(손실) (단위 : 원) | H69: 42 | I69: 42 | J69: -45 | K69: -45 | M69: 중단영업희석주당이익(손실) (단위 : 원) | N69: -169 | O69: -228 | P69: -185
B70: 부채총계 | C70: 3799544705473 | D70: 3307593220262 | G70: 중단영업희석주당이익(손실) (단위 : 원) | H70: 42 | I70: 42 | J70: -45 | K70: -45
B71: 자본
B72: 지배기업의 소유주에게 귀속되는 자본 | C72: 3357851750573 | D72: 2490054967099
B73: 자본금 | C73: 944596945000 | D73: 944596945000
B74: 자본잉여금 | C74: 1092202306315 | D74: 1092001144057
B75: 기타자본구성요소 | C75: -34121410840 | D75: -34121410840
B76: 기타포괄손익누계액 | C76: 793494784177 | D76: -101713579335
B77: 이익잉여금(결손금) | C77: 561679125921 | D77: 589291868217
B78: 비지배지분 | C78: 55216347417 | D78: -73638071643
B79: 자본총계 | C79: 3413068097990 | D79: 2416416895456
B80: 자본과부채총계 | C80: 7212612803463 | D80: 5724010115718
B83: 금융부채의 공시
B84: 금융부채의 범주별 공시
B85: 당분기말 | C85: (단위 : 천원)
C86: 파생상품 | D86: 당기손익인식금융부채 | E86: 상각후원가측정금융부채 | F86: 공정가치로 측정하는 금융부채
B87: 매입채무 | C87: 0 | D87: 0 | E87: 190922837 | F87: 190922837
B88: 미지급금 | C88: 0 | D88: 0 | E88: 154861537 | F88: 154861537
B89: 단기미지급비용 | C89: 0 | D89: 0 | E89: 51747777 | F89: 51747777
A90: IBD | B90: 금융기관 차입금(사채 제외) | C90: 0 | D90: 0 | E90: 235965000 | F90: 235965000
A91: IBD | B91: 사채 | C91: 0 | D91: 0 | E91: 299336786 | F91: 299336786
B92: 보증금부채 | C92: 0 | D92: 0 | E92: 41359 | F92: 41359
B93: 장기미지급비용 | C93: 0 | D93: 0 | E93: 241265 | F93: 241265
B94: 파생상품부채 | C94: 1470713 | D94: 0 | E94: 0 | F94: 1470713
A95: IBD | B95: 리스부채 | C95: 0 | D95: 0 | E95: 137520503 | F95: 137520503
B96: 금융부채 | C96: 1470713 | D96: 0 | E96: 1070637064 | F96: 1072107777
B99: 20. 기타금융부채 - 연결 (연결)
B101: 기타금융부채
B103: 기타금융부채
B104: 당분기말 | C104: (단위 : 천원)
C105: 기타금융부채
B106: 유동 보증금부채 | C106: 0
B107: 유동으로 분류되는 미지급비용 | C107: 96861847
B108: 유동파생상품부채 | C108: 1470713
B109: 유동 리스부채 | C109: 26528485 | E109: =C109+C114 -> 137520503
B110: 기타유동금융부채 | C110: 124861045
B111: 비유동 보증금부채 | C111: 41359
B112: 비유동으로 분류되는 미지급비용 | C112: 25754561
B113: 비유동파생상품부채 | C113: 0
B114: 비유동 리스부채 | C114: 110992018
B115: 기타비유동금융부채 | C115: 136787938

Sheet LIG넥스원
A1: LIG디펜스앤에어로스페이스
A2: 45777
G4: (단위: 백만)
B5: 주가 | C5: 유통주식수 | D5: 시가총액 | E5: ibd | F5: ltm ebit | G5: tax rate
B6: 248000 | C6: =D25 -> 21794360 | D6: =(B6*C6)/10^6 -> 5405001.3 | E6: =SUMIF(A:A,E5,E:E)/10^3 -> 295353.18 | F6: =(H41+N41-J41)/10^6 -> 276386.04 | G6: =IF(F6<=200, 0.99, IF(F6<=20000, 0.209, IF(F6<=300000, 0.231, 0.264))) -> 0.231
B9: 4. 주식의 총수 등
B11: 가. 주식의 총수 현황
B12: 당사의 정관상 발행가능한 주식의 총수는 100,000,000주이며, 발행한 주식의 총수는 보통주 22,000,000주 입니다. 2024년 12월 31일 기준 및 보고서 제출일 현재 당사가 보통주 외에 발행한 주식은 없습니다. | C12: 2024.12.31 | D12: )
B13: (기준일 : | C13: 45747 | D13: ) | E13: (단위 : 주, %) | G13: 비고
B14: 구 분 | D14: 주식의 종류 | G14: 비고
D15: 보통주 | E15: 우선주 | F15: 합계
B16: Ⅰ. 발행할 주식의 총수 | D16: 90000000 | E16: 10000000 | F16: 100000000 | G16: -
B17: Ⅱ. 현재까지 발행한 주식의 총수 | D17: 22000000 | E17: - | F17: 22000000 | G17: -
B18: Ⅲ. 현재까지 감소한 주식의 총수 | D18: - | E18: - | F18: - | G18: -
C19: 1. 감자 | D19: - | E19: - | F19: - | G19: -
C20: 2. 이익소각 | D20: - | E20: - | F20: - | G20: -
C21: 3. 상환주식의 상환 | D21: - | E21: - | F21: - | G21: -
C22: 4. 기타 | D22: - | E22: - | F22: - | G22: -
B23: Ⅳ. 발행주식의 총수 (Ⅱ-Ⅲ) | D23: 22000000 | E23: - | F23: 22000000 | G23: -
B24: Ⅴ. 자기주식수 | D24: 205640 | E24: - | F24: 205640 | G24: -
B25: Ⅵ. 유통주식수 (Ⅳ-Ⅴ) | D25: 21794360 | E25: - | F25: 21794360 | G25: -
B26: Ⅶ. 자기주식 보유비율 | D26: 0.93 | E26: - | F26: 0.93 | G26: -
D27: - | E27: - | F27: - | G27: -
B30: 2-1. 연결 재무상태표 | G30: 2-2. 연결 포괄손익계산서 | M30: 2-2. 연결 포괄손익계산서
B31: 연결 재무상태표 | G31: 연결 포괄손익계산서 | M31: 연결 포괄손익계산서
B32: 제 24 기 1분기말 2025.03.31 현재 | G32: 제 24 기 1분기 2025.01.01 부터 2025.03.31 까지 | M32: 제 23 기 2024.01.01 부터 2024.12.31 까지
B33: 제 23 기말 2024.12.31 현재 | G33: 제 23 기 1분기 2024.01.01 부터 2024.03.31 까지 | M33: 제 22 기 2023.01.01 부터 2023.12.31 까지
B34: (단위 : 원) | G34: (단위 : 원) | M34: 제 21 기 2022.01.01 부터 2022.12.31 까지
C35: 제 24 기 1분기말 | D35: 제 23 기말 | H35: 제 24 기 1분기 | J35: 제 23 기 1분기 | M35: (단위 : 원)
B36: 자산 | H36: 3개월 | I36: 누적 | J36: 3개월 | K36: 누적 | N36: 제 23 기 | O36: 제 22 기 | P36: 제 21 기
B37: 유동자산 | C37: 4364826755192 | D37: 3894568274428 | G37: 수익(매출액) | H37: 907622648219 | I37: 907622648219 | J37: 763536502941 | K37: 763536502941 | M37: 수익(매출액) | N37: 3276339508425 | O37: 2308571092877 | P37: 2220751868438
B38: 현금및현금성자산 | C38: 122982509455 | D38: 546947952484 | G38: 매출원가 | H38: 733980258876 | I38: 733980258876 | J38: 657287629253 | K38: 657287629253 | M38: 매출원가 | N38: 2823712221178 | O38: 1961778919898 | P38: 1894209846592
B39: 매출채권 | C39: 299191431810 | D39: 364450287404 | G39: 매출총이익 | H39: 173642389343 | I39: 173642389343 | J39: 106248873688 | K39: 106248873688 | M39: 매출총이익 | N39: 452627287247 | O39: 346792172979 | P39: 326542021846
B40: 유동계약자산 | C40: 706348728363 | D40: 458999591583 | G40: 판매비와관리비 | H40: 60045463407 | I40: 60045463407 | J40: 39258594314 | K40: 39258594314 | M40: 판매비와관리비 | N40: 222847894976 | O40: 160413734039 | P40: 147430283974
B41: 유동재고자산 | C41: 301998296897 | D41: 363527737579 | G41: 영업이익(손실) | H41: 113596925936 | I41: 113596925936 | J41: 66990279374 | K41: 66990279374 | M41: 영업이익(손실) | N41: 229779392271 | O41: 186378438940 | P41: 179111737872
B42: 기타유동금융자산 | C42: 97493572159 | D42: 82169825799 | G42: 금융수익 | H42: 2487341066 | I42: 2487341066 | J42: 8947541229 | K42: 8947541229 | M42: 금융수익 | N42: 27824271978 | O42: 9578470422 | P42: 34411637673
B43: 기타유동자산 | C43: 2836812207908 | D43: 2078472879579 | G43: 금융원가 | H43: 3499735850 | I43: 3499735850 | J43: 16764956793 | K43: 16764956793 | M43: 금융원가 | N43: 84519397962 | O43: 15281784063 | P43: 36297682943
B44: 당기법인세자산 | C44: 8600 | D44: 0 | G44: 기타이익 | H44: 4126760355 | I44: 4126760355 | J44: 23001008528 | K44: 23001008528 | M44: 기타이익 | N44: 86274860803 | O44: 25590118881 | P44: 49157184720
B45: 비유동자산 | C45: 2253108836826 | D45: 2230696378789 | G45: 기타손실 | H45: 14477634940 | I45: 14477634940 | J45: 13018872641 | K45: 13018872641 | M45: 기타손실 | N45: 49798805244 | O45: 21363906572 | P45: 70782113607
B46: 비유동매출채권 | C46: 8855579171 | D46: 4407734259 | G46: 지분법이익 | H46: 365642462 | I46: 365642462 | J46: 252250388 | K46: 252250388 | M46: 지분법이익 | N46: 68898126 | O46: 101108735 | P46: 2171189980
B47: 유형자산 | C47: 1398356579725 | D47: 1371400306134 | G47: 법인세비용차감전순이익(손실) | H47: 102599299029 | I47: 102599299029 | J47: 69407250085 | K47: 69407250085 | M47: 법인세비용차감전순이익(손실) | N47: 209629219972 | O47: 185002446343 | P47: 157771953695
B48: 투자부동산 | C48: 4099143034 | D48: 4108934797 | G48: 법인세비용(수익) | H48: 19767092549 | I48: 19767092549 | J48: 8832431440 | K48: 8832431440 | M48: 법인세비용(수익) | N48: -7019499582 | O48: 10040303224 | P48: 34832366324
B49: 무형자산 | C49: 638072265233 | D49: 629237817038 | G49: 당기순이익(손실) | H49: 82832206480 | I49: 82832206480 | J49: 60574818645 | K49: 60574818645 | M49: 당기순이익(손실) | N49: 216648719554 | O49: 174962143119 | P49: 122939587371
B50: 관계기업 및 공동기업투자 | C50: 4882183271 | D50: 3331540809 | G50: 당기순이익(손실)의 귀속 | M50: 당기순이익(손실)의 귀속
B51: 기타비유동금융자산 | C51: 79111172470 | D51: 78594391037 | G51: 지배기업의 소유주에게 귀속되는 당기순이익(손실) | H51: 84223792038 | I51: 84223792038 | J51: 60574818645 | K51: 60574818645 | M51: 지배기업의 소유주에게 귀속되는 당기순이익(손실) | N51: 221711612922 | O51: 174962143119 | P51: 122939587371
B52: 기타비유동자산 | C52: 14770782309 | D52: 10771626186 | G52: 비지배지분에 귀속되는 당기순이익(손실) | H52: -1391585558 | I52: -1391585558 | J52: 0 | K52: 0 | M52: 비지배지분에 귀속되는 당기순이익(손실) | N52: -5062893368 | O52: 0 | P52: 0
B53: 순확정급여자산 | C53: 22070580221 | D53: 31808037817 | G53: 기타포괄손익 | H53: -588608014 | I53: -588608014 | J53: -344767447 | K53: -344767447 | M53: 기타포괄손익 | N53: -16521276914 | O53: -25090661640 | P53: 75088327441
B54: 이연법인세자산 | C54: 82890551392 | D54: 97035990712 | G54: 후속적으로 당기손익으로 재분류될 수 있는 항목 | M54: 후속적으로 당기손익으로 재분류될 수 있는 항목
B55: 자산총계 | C55: 6617935592018 | D55: 6125264653217 | G55: 해외사업장환산외환차이(세후기타포괄손익) | H55: -556187074 | I55: -556187074 | J55: 0 | K55: 0 | M55: 해외사업장환산외환차이(세후기타포괄손익) | N55: 12571414060 | O55: 0 | P55: 0
B56: 부채 | G56: 당기손익으로 재분류되는 지분법 적용대상 관계기업과 공동기업의 세후기타포괄손익에 대한 지분 | H56: 0 | J56: 0 | K56: 0 | M56: 당기손익으로 재분류되는 지분법 적용대상 관계기업과 공동기업의 세후기타포괄손익에 대한 지분 | N56: 0 | O56: 0 | P56: -155834631
B57: 유동부채 | C57: 5087388915252 | D57: 4616518043951 | G57: 후속적으로 당기손익으로 재분류되지 않는 항목 | M57: 후속적으로 당기손익으로 재분류되지 않는 항목
B58: 유동 차입금(사채 포함) | C58: 208983659706 | D58: 203420867752 | G58: 기타포괄손익-공정가치 측정 금융자산 평가손익 적립금 | H58: 24527949 | I58: 24527949 | J58: 25479111 | K58: 25479111 | M58: 기타포괄손익-공정가치 측정 금융자산 평가손익 적립금 | N58: 25479111 | O58: 57867673 | P58: -119131519
B59: 단기매입채무 | C59: 256448599957 | D59: 363833512538 | G59: 세후기타포괄손익, 확정급여제도의 재측정손익 | H59: -418115769 | I59: -418115769 | J59: -393931947 | K59: -393931947 | M59: 세후기타포괄손익, 확정급여제도의 재측정손익 | N59: -29863042795 | O59: -25142190723 | P59: 20135116455
B60: 유동계약부채 | C60: 3523921205209 | D60: 3457859685691 | G60: 세후기타포괄손익, 자산재평가차익(차손) | H60: 361166880 | I60: 361166880 | J60: 23685389 | K60: 23685389 | M60: 세후기타포괄손익, 자산재평가차익(차손) | N60: 773282428 | O60: 0 | P60: 55225216673
B61: 유동충당부채 | C61: 66954957087 | D61: 76113239891 | G61: 당기손익으로 재분류되지 않는 지분법 적용대상 관계기업과 공동기업의 세후기타포괄손익에 대한 지분 | H61: 0 | J61: 0 | K61: 0 | M61: 당기손익으로 재분류되지 않는 지분법 적용대상 관계기업과 공동기업의 세후기타포괄손익에 대한 지분 | N61: -28409718 | O61: -6338590 | P61: 2960463
B62: 기타유동금융부채 | C62: 962404625714 | D62: 415321291898 | G62: 총포괄손익 | H62: 82243598466 | I62: 82243598466 | J62: 60230051198 | K62: 60230051198 | M62: 총포괄손익 | N62: 200127442640 | O62: 149871481479 | P62: 198027914812
B63: 기타 유동부채 | C63: 50135325949 | D63: 78073572991 | G63: 포괄손익의 귀속 | M63: 포괄손익의 귀속
B64: 당기법인세부채 | C64: 18540541630 | D64: 21895873190 | G64: 포괄손익, 지배기업의 소유주에게 귀속되는 지분 | H64: 83831508914 | I64: 83831508914 | J64: 60230051198 | K64: 60230051198 | M64: 포괄손익, 지배기업의 소유주에게 귀속되는 지분 | N64: 200771168664 | O64: 149871481479 | P64: 198027914812
B65: 비유동부채 | C65: 260511508615 | D65: 271311374204 | G65: 포괄손익, 비지배지분 | H65: -1587910448 | I65: -1587910448 | J65: 0 | K65: 0 | M65: 포괄손익, 비지배지분 | N65: -643726024 | O65: 0 | P65: 0
B66: 장기차입금(사채 포함), 총액 | C66: 178377793530 | D66: 188002167810 | G66: 주당이익 | M66: 주당이익
B67: 비유동계약부채 | C67: 0 | D67: 1237728240 | G67: 기본주당이익(손실) (단위 : 원) | H67: 3864 | I67: 3864 | J67: 2779 | K67: 2779 | M67: 기본주당이익(손실) (단위 : 원) | N67: 10173 | O67: 8028 | P67: 5641
B68: 기타비유동금융부채 | C68: 28806988170 | D68: 30298199325
B69: 기타 비유동 부채 | C69: 53326726915 | D69: 51773278829
B70: 부채총계 | C70: 5347900423867 | D70: 4887829418155
B71: 자본
B72: 지배기업의 소유주에게 귀속되는 자본 | C72: 1242212522305 | D72: 1210681900588
B73: 자본금 | C73: 110000000000 | D73: 110000000000
B74: 자본잉여금 | C74: 142100550500 | D74: 142100550500
B75: 기타자본구성요소 | C75: -5251979178 | D75: -5260182234
B76: 기타포괄손익누계액 | C76: 56307062923 | D76: 56701972300
B77: 이익잉여금(결손금) | C77: 939056888060 | D77: 907139560022
B78: 비지배지분 | C78: 27822645846 | D78: 26753334474
B79: 자본총계 | C79: 1270035168151 | D79: 1237435235062
B80: 자본과부채총계 | C80: 6617935592018 | D80: 6125264653217
B83: 금융부채의 공시
B84: 금융부채의 범주별 공시
B85: 당분기말 | C85: (단위 : 천원)
E86: 상각후원가로 측정하는 금융부채, 범주 | F86: 당기손익인식금융부채
B87: 유동금융부채의 범주
A88: ibd | B88: 유동금융부채의 범주 | C88: 유동 차입금(사채 포함) | E88: 208983660 | F88: 0
C89: 유동 차입금(사채 포함) | D89: 단기차입금 | E89: 169995402 | F89: 0
D90: 유동성장기부채 | E90: 38988258 | F90: 0
C91: 유동매입채무 | E91: 256448600 | F91: 0
C92: 기타유동금융부채 | E92: 920343150 | F92: 3835158
C93: 기타유동금융부채 | D93: 단기미지급금 | E93: 144312603 | F93: 0
D94: 단기미지급비용 | E94: 757609544 | F94: 0
A95: ibd | D95: 유동 리스부채 | E95: 18421003 | F95: 0
D96: 유동파생상품부채 | E96: 0 | F96: 3835158
C97: 유동 금융부채 합계 | E97: 1385775410 | F97: 3835158
B98: 비유동 금융부채의 범주
A99: ibd | B99: 비유동 금융부채의 범주 | C99: 비유동차입금 | E99: 41815520 | F99: 136562274
C100: 비유동차입금 | D100: 장기차입금 | E100: 41815520 | F100: 0
D101: 교환사채 | E101: 0 | F101: 136562274
C102: 기타비유동금융부채 | E102: 26132996 | F102: 2673993
A103: ibd | C103: 기타비유동금융부채 | D103: 비유동 리스부채 | E103: 26132996 | F103: 0
D104: 비유동파생상품부채 | E104: 0 | F104: 2673993
C105: 비유동 금융부채 합계 | E105: 67948516 | F105: 139236267
B106: 총 금융부채 | E106: 1453723926 | F106: 143071425
